verysimplemodule_lais/__init__.py
verysimplemodule_lais/baixar_arquivo.py
verysimplemodule_lais-0.0.1.7.dist-info/METADATA
verysimplemodule_lais-0.0.1.7.dist-info/WHEEL
verysimplemodule_lais-0.0.1.7.dist-info/top_level.txt
verysimplemodule_lais-0.0.1.7.dist-info/RECORD
