Metadata-Version: 2.1
Name: verysimplemodule-lais
Version: 0.0.1.7
Summary: Pacote para baixar arquivo
Author: Lais Sousa
Author-email: <laissouroch@gmail.com>
Keywords: python,first package
Classifier: Development Status :: 3 - Alpha
Classifier: Intended Audience :: Education
Classifier: Programming Language :: Python :: 2
Classifier: Programming Language :: Python :: 3
Classifier: Operating System :: MacOS :: MacOS X
Classifier: Operating System :: Microsoft :: Windows
Requires-Dist: requests
